{
  "id": "General",
  "lastKnownVersion": "1.43.0",
  "highestInstalledVersion": "1.43.0",
  "showedNetworkOptIn": true,
  "theme": "OS_THEME",
  "telemetryAnonymousId": "dc4446e8-bc36-4d1a-b0f4-8a5b46857a77",
  "userCreatedAt": 1713276455173,
  "cloudFeatureRolloutAccess": {
    "GEN_AI_COMPASS": true
  },
  "networkTraffic": true,
  "readOnly": false,
  "enableShell": true,
  "enableMaps": true,
  "enableGenAIFeatures": true,
  "enableFeedbackPanel": true,
  "trackUsageStatistics": true,
  "autoUpdates": true,
  "protectConnectionStrings": false,
  "enableDevTools": false,
  "showKerberosPasswordField": false,
  "showOIDCDeviceAuthFlow": false,
  "persistOIDCTokens": true,
  "installURLHandlers": true,
  "protectConnectionStringsForNewConnections": false,
  "atlasServiceBackendPreset": "atlas",
  "enableAtlasSearchIndexes": true,
  "enableImportExport": true,
  "enableAggregationBuilderRunPipeline": true,
  "enableExplainPlan": true,
  "enableAggregationBuilderExtraOptions": true,
  "enableGenAISampleDocumentPassing": false,
  "enableHackoladeBanner": true,
  "enablePerformanceAdvisorBanner": false,
  "maximumNumberOfActiveConnections": 10,
  "showDevFeatureFlags": false,
  "enableOidc": false,
  "newExplainPlan": false,
  "showInsights": false,
  "enableRenameCollectionModal": false,
  "enableNewMultipleConnectionSystem": false
}